setup.py
bin/mdiblasiofunniest-joke
mdiblasiofunniest/__init__.py
mdiblasiofunniest.egg-info/PKG-INFO
mdiblasiofunniest.egg-info/SOURCES.txt
mdiblasiofunniest.egg-info/dependency_links.txt
mdiblasiofunniest.egg-info/not-zip-safe
mdiblasiofunniest.egg-info/top_level.txt