Metadata-Version: 1.0
Name: mdiblasiofunniest
Version: 0.3
Summary: The funniest joke in the world
Home-page: http://github.com/mdiblasio/funniest
Author: Michael DiBlasio
Author-email: mdiblasio@google.com
License: dibs
Platform: UNKNOWN
